[
    {
        "inputs": [
            {
                "internalType": "address",
                "name": "dapp",
                "type": "address"
            }
        ],
        "stateMutability": "nonpayable",
        "type": "constructor"
    },
    {
        "anonymous": false,
        "inputs": [
            {
                "indexed": false,
                "internalType": "address",
                "name": "child",
                "type": "address"
            },
            {
                "indexed": false,
                "internalType": "uint256",
                "name": "bonus",
                "type": "uint256"
            },
            {
                "indexed": false,
                "internalType": "uint8",
                "name": "maxLevelRate",
                "type": "uint8"
            },
            {
                "indexed": false,
                "internalType": "uint8",
                "name": "v5Count",
                "type": "uint8"
            },
            {
                "indexed": false,
                "internalType": "uint256",
                "name": "dai",
                "type": "uint256"
            }
        ],
        "name": "BonusInfo",
        "type": "event"
    },
    {
        "anonymous": false,
        "inputs": [
            {
                "indexed": true,
                "internalType": "address",
                "name": "previousOwner",
                "type": "address"
            },
            {
                "indexed": true,
                "internalType": "address",
                "name": "newOwner",
                "type": "address"
            }
        ],
        "name": "OwnershipTransferred",
        "type": "event"
    },
    {
        "inputs": [
            {
                "internalType": "address",
                "name": "",
                "type": "address"
            },
            {
                "internalType": "address",
                "name": "",
                "type": "address"
            },
            {
                "internalType": "uint32",
                "name": "",
                "type": "uint32"
            }
        ],
        "name": "_accountClaimInfo",
        "outputs": [
            {
                "internalType": "uint256",
                "name": "",
                "type": "uint256"
            }
        ],
        "stateMutability": "view",
        "type": "function"
    },
    {
        "inputs": [],
        "name": "getParams",
        "outputs": [
            {
                "internalType": "address",
                "name": "dapp",
                "type": "address"
            },
            {
                "internalType": "address",
                "name": "unms",
                "type": "address"
            },
            {
                "internalType": "address",
                "name": "topAddress",
                "type": "address"
            }
        ],
        "stateMutability": "view",
        "type": "function"
    },
    {
        "inputs": [
            {
                "internalType": "address",
                "name": "userAddress",
                "type": "address"
            },
            {
                "internalType": "uint256",
                "name": "orderIndex",
                "type": "uint256"
            }
        ],
        "name": "getUserInfo",
        "outputs": [
            {
                "internalType": "address",
                "name": "parent",
                "type": "address"
            },
            {
                "internalType": "uint8",
                "name": "levelRate",
                "type": "uint8"
            },
            {
                "internalType": "uint256",
                "name": "usdtAmount",
                "type": "uint256"
            },
            {
                "internalType": "uint32",
                "name": "investTime",
                "type": "uint32"
            }
        ],
        "stateMutability": "view",
        "type": "function"
    },
    {
        "inputs": [],
        "name": "owner",
        "outputs": [
            {
                "internalType": "address",
                "name": "",
                "type": "address"
            }
        ],
        "stateMutability": "view",
        "type": "function"
    },
    {
        "inputs": [],
        "name": "renounceOwnership",
        "outputs": [],
        "stateMutability": "nonpayable",
        "type": "function"
    },
    {
        "inputs": [
            {
                "internalType": "address",
                "name": "account",
                "type": "address"
            },
            {
                "internalType": "address",
                "name": "child",
                "type": "address"
            },
            {
                "internalType": "uint32",
                "name": "orderIndex",
                "type": "uint32"
            },
            {
                "internalType": "uint256",
                "name": "claimAmount",
                "type": "uint256"
            }
        ],
        "name": "setAccountInfo",
        "outputs": [],
        "stateMutability": "nonpayable",
        "type": "function"
    },
    {
        "inputs": [
            {
                "internalType": "address",
                "name": "newOwner",
                "type": "address"
            }
        ],
        "name": "transferOwnership",
        "outputs": [],
        "stateMutability": "nonpayable",
        "type": "function"
    },
    {
        "inputs": [
            {
                "internalType": "uint32",
                "name": "orderIndex",
                "type": "uint32"
            },
            {
                "internalType": "address[]",
                "name": "childs",
                "type": "address[]"
            }
        ],
        "name": "unmsClaimTeamBonus",
        "outputs": [],
        "stateMutability": "nonpayable",
        "type": "function"
    },
    {
        "inputs": [
            {
                "internalType": "address",
                "name": "account",
                "type": "address"
            },
            {
                "internalType": "address",
                "name": "child",
                "type": "address"
            },
            {
                "internalType": "uint256",
                "name": "orderIndex",
                "type": "uint256"
            }
        ],
        "name": "unmsQuerySingle",
        "outputs": [
            {
                "internalType": "uint256",
                "name": "totalBonus",
                "type": "uint256"
            },
            {
                "internalType": "uint8",
                "name": "maxLevelRate",
                "type": "uint8"
            },
            {
                "internalType": "uint8",
                "name": "v5Count",
                "type": "uint8"
            },
            {
                "internalType": "uint256",
                "name": "dai",
                "type": "uint256"
            }
        ],
        "stateMutability": "view",
        "type": "function"
    },
    {
        "inputs": [
            {
                "internalType": "address",
                "name": "account",
                "type": "address"
            },
            {
                "internalType": "uint32",
                "name": "orderIndex",
                "type": "uint32"
            },
            {
                "internalType": "address[]",
                "name": "childs",
                "type": "address[]"
            }
        ],
        "name": "unmsQueryTeamBonus",
        "outputs": [
            {
                "internalType": "uint256",
                "name": "totalBonus",
                "type": "uint256"
            }
        ],
        "stateMutability": "view",
        "type": "function"
    },
    {
        "inputs": [
            {
                "internalType": "address",
                "name": "to",
                "type": "address"
            },
            {
                "internalType": "uint256",
                "name": "amount",
                "type": "uint256"
            }
        ],
        "name": "unmsReleaseToken",
        "outputs": [],
        "stateMutability": "nonpayable",
        "type": "function"
    }
]